{
    "sourceFile": "src/App.js",
    "activeCommit": 0,
    "commits": [
        {
            "activePatchIndex": 9,
            "patches": [
                {
                    "date": 1752058703396,
                    "content": "Index: \n===================================================================\n--- \n+++ \n"
                },
                {
                    "date": 1752058757120,
                    "content": "Index: \n===================================================================\n--- \n+++ \n@@ -132,9 +132,9 @@\n           <Route path=\"/Page51\" element={<Page51/>} />\r\n           <Route path=\"/GuestFaculty\" element={<Page52 />} />\r\n          <Route path=\"/board-of-studies\" element={<Page53 />} />\r\n          <Route path=\"/Seminar\" element={<Seminar />} />\r\n-        <Route path=\"/Conference\" element={<Conference />} />\r\n+         <Route path=\"/Conference\" element={<Conference />} />\r\n         <Route path=\"/SmartClass\" element={<SmartClass />} />\r\n         </Routes>\r\n \r\n \r\n"
                },
                {
                    "date": 1752058916364,
                    "content": "Index: \n===================================================================\n--- \n+++ \n@@ -53,33 +53,27 @@\n import Page50 from './page/Page50';\r\n import Page51 from './page/Page51';\r\n import Page52 from './page/Page52';\r\n import Page53 from './page/page53';\r\n+\r\n import Seminar from './page/Seminar';\r\n import Conference from './page/Conference';\r\n import SmartClass from './page/SmartClass';\r\n \r\n-\r\n-\r\n import News1 from './News/News1';\r\n import News2 from './News/News2';\r\n import News3 from './News/News3';\r\n import News4 from './News/News4';\r\n import News5 from './News/News5';\r\n import News6 from './News/News6';\r\n import News7 from './News/News7';\r\n \r\n-\r\n-\r\n-\r\n function App() {\r\n   return (\r\n-    < >\r\n-      \r\n+    <>\r\n       <BrowserRouter>\r\n-      \r\n         <Routes>\r\n-        <Route path=\"/\" element={<MainContent />} />\r\n+          <Route path=\"/\" element={<MainContent />} />\r\n           <Route path=\"/MA\" element={<Page1 />} />\r\n           <Route path=\"/PhD\" element={<Page2 />} />\r\n           <Route path=\"/About\" element={<About />} />\r\n           <Route path=\"/Staff\" element={<Page4 />} />\r\n@@ -116,45 +110,36 @@\n           <Route path=\"/Page35\" element={<Page35 />} />\r\n           <Route path=\"/Page36\" element={<Page36 />} />\r\n           <Route path=\"/Page37\" element={<Page37 />} />\r\n           <Route path=\"/Page38\" element={<Page38 />} />\r\n-          <Route path=\"/Page39\" element={<Page39/>} />\r\n-          <Route path=\"/Page40\" element={<Page40/>} />\r\n-          <Route path=\"/Page41\" element={<Page41/>} />\r\n-          <Route path=\"/Page42\" element={<Page42/>} />\r\n-          <Route path=\"/Page44\" element={<Page44/>} />\r\n-          <Route path=\"/Page43\" element={<Page43/>} />\r\n-          <Route path=\"/Page45\" element={<Page45/>} />\r\n-          <Route path=\"/Page46\" element={<Page46/>} />\r\n-          <Route path=\"/Page47\" element={<Page47/>} />\r\n-          <Route path=\"/Page48\" element={<Page48/>} />\r\n-          <Route path=\"/Page49\" element={<Page49/>} />\r\n-          <Route path=\"/Page50\" element={<Page50/>} />\r\n-          <Route path=\"/Page51\" element={<Page51/>} />\r\n+          <Route path=\"/Page39\" element={<Page39 />} />\r\n+          <Route path=\"/Page40\" element={<Page40 />} />\r\n+          <Route path=\"/Page41\" element={<Page41 />} />\r\n+          <Route path=\"/Page42\" element={<Page42 />} />\r\n+          <Route path=\"/Page43\" element={<Page43 />} />\r\n+          <Route path=\"/Page44\" element={<Page44 />} />\r\n+          <Route path=\"/Page45\" element={<Page45 />} />\r\n+          <Route path=\"/Page46\" element={<Page46 />} />\r\n+          <Route path=\"/Page47\" element={<Page47 />} />\r\n+          <Route path=\"/Page48\" element={<Page48 />} />\r\n+          <Route path=\"/Page49\" element={<Page49 />} />\r\n+          <Route path=\"/Page50\" element={<Page50 />} />\r\n+          <Route path=\"/Page51\" element={<Page51 />} />\r\n           <Route path=\"/GuestFaculty\" element={<Page52 />} />\r\n-         <Route path=\"/board-of-studies\" element={<Page53 />} />\r\n-         <Route path=\"/Seminar\" element={<Seminar />} />\r\n-         <Route path=\"/Conference\" element={<Conference />} />\r\n-        <Route path=\"/SmartClass\" element={<SmartClass />} />\r\n-        </Routes>\r\n-\r\n-\r\n-\r\n-\r\n-          \r\n-          \r\n+          <Route path=\"/board-of-studies\" element={<Page53 />} />\r\n+          <Route path=\"/Seminar\" element={<Seminar />} />\r\n+          <Route path=\"/Conference\" element={<Conference />} />\r\n+          <Route path=\"/SmartClass\" element={<SmartClass />} />\r\n           <Route path=\"/News1\" element={<News1 />} />\r\n           <Route path=\"/News2\" element={<News2 />} />\r\n           <Route path=\"/News3\" element={<News3 />} />\r\n           <Route path=\"/News4\" element={<News4 />} />\r\n           <Route path=\"/News5\" element={<News5 />} />\r\n           <Route path=\"/News6\" element={<News6 />} />\r\n           <Route path=\"/News7\" element={<News7 />} />\r\n         </Routes>\r\n-       \r\n       </BrowserRouter>\r\n-      \r\n-    </ >\r\n+    </>\r\n   );\r\n }\r\n \r\n export default App;\r\n"
                },
                {
                    "date": 1752061324602,
                    "content": "Index: \n===================================================================\n--- \n+++ \n@@ -55,9 +55,9 @@\n import Page52 from './page/Page52';\r\n import Page53 from './page/page53';\r\n \r\n import Seminar from './page/Seminar';\r\n-import Conference from './page/Conference';\r\n+import ConferenceRoom from './page/ConferenceRoom';\r\n import SmartClass from './page/SmartClass';\r\n \r\n import News1 from './News/News1';\r\n import News2 from './News/News2';\r\n@@ -126,9 +126,9 @@\n           <Route path=\"/Page51\" element={<Page51 />} />\r\n           <Route path=\"/GuestFaculty\" element={<Page52 />} />\r\n           <Route path=\"/board-of-studies\" element={<Page53 />} />\r\n           <Route path=\"/Seminar\" element={<Seminar />} />\r\n-          <Route path=\"/Conference\" element={<Conference />} />\r\n+          <Route path=\"/ConferenceRoom\" element={<ConferenceRoom />} />\r\n           <Route path=\"/SmartClass\" element={<SmartClass />} />\r\n           <Route path=\"/News1\" element={<News1 />} />\r\n           <Route path=\"/News2\" element={<News2 />} />\r\n           <Route path=\"/News3\" element={<News3 />} />\r\n"
                },
                {
                    "date": 1752071154944,
                    "content": "Index: \n===================================================================\n--- \n+++ \n@@ -55,9 +55,9 @@\n import Page52 from './page/Page52';\r\n import Page53 from './page/page53';\r\n \r\n import Seminar from './page/Seminar';\r\n-import ConferenceRoom from './page/ConferenceRoom';\r\n+import Conference from './page/ConferenceRoom';\r\n import SmartClass from './page/SmartClass';\r\n \r\n import News1 from './News/News1';\r\n import News2 from './News/News2';\r\n@@ -126,9 +126,9 @@\n           <Route path=\"/Page51\" element={<Page51 />} />\r\n           <Route path=\"/GuestFaculty\" element={<Page52 />} />\r\n           <Route path=\"/board-of-studies\" element={<Page53 />} />\r\n           <Route path=\"/Seminar\" element={<Seminar />} />\r\n-          <Route path=\"/ConferenceRoom\" element={<ConferenceRoom />} />\r\n+          <Route path=\"/Conference\" element={<ConferenceRoom />} />\r\n           <Route path=\"/SmartClass\" element={<SmartClass />} />\r\n           <Route path=\"/News1\" element={<News1 />} />\r\n           <Route path=\"/News2\" element={<News2 />} />\r\n           <Route path=\"/News3\" element={<News3 />} />\r\n"
                },
                {
                    "date": 1752071342399,
                    "content": "Index: \n===================================================================\n--- \n+++ \n@@ -55,9 +55,9 @@\n import Page52 from './page/Page52';\r\n import Page53 from './page/page53';\r\n \r\n import Seminar from './page/Seminar';\r\n-import Conference from './page/ConferenceRoom';\r\n+import Conference from './page/Conference'; // ✅ Corrected import\r\n import SmartClass from './page/SmartClass';\r\n \r\n import News1 from './News/News1';\r\n import News2 from './News/News2';\r\n@@ -89,11 +89,11 @@\n           <Route path=\"/Library\" element={<Page14 />} />\r\n           <Route path=\"/page15\" element={<Page15 />} />\r\n           <Route path=\"/page16\" element={<Page16 />} />\r\n           <Route path=\"/Disaster_management\" element={<Page17 />} />\r\n+          <Route path=\"/Scipt_writing\" element={<Page18 />} />\r\n           <Route path=\"/Digital_education\" element={<Page19 />} />\r\n           <Route path=\"/Film_screening\" element={<Page20 />} />\r\n-          <Route path=\"/Scipt_writing\" element={<Page18 />} />\r\n           <Route path=\"/Refresher_training\" element={<Page21 />} />\r\n           <Route path=\"/Student_activities\" element={<Page22 />} />\r\n           <Route path=\"/AdvisoryCommittee\" element={<Page23 />} />\r\n           <Route path=\"/Some_moments\" element={<Page24 />} />\r\n@@ -125,11 +125,15 @@\n           <Route path=\"/Page50\" element={<Page50 />} />\r\n           <Route path=\"/Page51\" element={<Page51 />} />\r\n           <Route path=\"/GuestFaculty\" element={<Page52 />} />\r\n           <Route path=\"/board-of-studies\" element={<Page53 />} />\r\n+\r\n+          {/* ✅ Corrected routes */}\r\n           <Route path=\"/Seminar\" element={<Seminar />} />\r\n-          <Route path=\"/Conference\" element={<ConferenceRoom />} />\r\n+          <Route path=\"/Conference\" element={<Conference />} />\r\n           <Route path=\"/SmartClass\" element={<SmartClass />} />\r\n+\r\n+          {/* News pages */}\r\n           <Route path=\"/News1\" element={<News1 />} />\r\n           <Route path=\"/News2\" element={<News2 />} />\r\n           <Route path=\"/News3\" element={<News3 />} />\r\n           <Route path=\"/News4\" element={<News4 />} />\r\n"
                },
                {
                    "date": 1752083951575,
                    "content": "Index: \n===================================================================\n--- \n+++ \n@@ -0,0 +1,145 @@\n+import React from 'react';\r\n+import MainContent from './components/Main';\r\n+import Page1 from './page/page1';\r\n+import { BrowserRouter, Route, Routes } from 'react-router-dom';\r\n+import Page2 from './page/page2';\r\n+import About from './page/About';\r\n+import Page4 from './page/Page4';\r\n+import Page5 from './page/Page5';\r\n+import Page6 from './page/Page6';\r\n+import Page7 from './page/Page7';\r\n+import Page8 from './page/Page8';\r\n+import Page9 from './page/Page9';\r\n+import Page10 from './page/Page10';\r\n+import Page11 from './page/Page11';\r\n+import Page12 from './page/Page12';\r\n+import Page13 from './page/Page13';\r\n+import Page14 from './page/Page14';\r\n+import Page15 from './page/Page15';\r\n+import Page16 from './page/Page16';\r\n+import Page17 from './page/page17';\r\n+import Page18 from './page/Page18';\r\n+import Page19 from './page/Page19';\r\n+import Page20 from './page/Page20';\r\n+import Page21 from './page/Page21';\r\n+import Page22 from './page/Page22';\r\n+import Page23 from './page/Page23';\r\n+import Page24 from './page/Page24';\r\n+import Page25 from './page/Page25';\r\n+import Page26 from './page/Page26';\r\n+import Page27 from './page/Page27';\r\n+import Page28 from './page/Page28';\r\n+import Page29 from './page/Page29';\r\n+import Page30 from './page/Page30';\r\n+import Page31 from './page/Page31';\r\n+import Page32 from './page/Page32';\r\n+import Page33 from './page/Page33';\r\n+import Page34 from './page/Page34';\r\n+import Page35 from './page/Page35';\r\n+import Page36 from './page/Page36';\r\n+import Page37 from './page/Page37';\r\n+import Page38 from './page/Page38';\r\n+import Page39 from './page/Page39';\r\n+import Page40 from './page/Page40';\r\n+import Page41 from './page/Page41';\r\n+import Page42 from './page/Page42';\r\n+import Page43 from './page/Page43';\r\n+import Page44 from './page/Page44';\r\n+import Page45 from './page/Page45';\r\n+import Page46 from './page/Page46';\r\n+import Page47 from './page/Page47';\r\n+import Page48 from './page/Page48';\r\n+import Page49 from './page/Page49';\r\n+import Page50 from './page/Page50';\r\n+import Page51 from './page/Page51';\r\n+import Page52 from './page/Page52';\r\n+import Page53 from './page/page53';\r\n+\r\n+import Seminar from './page/Seminar';\r\n+import Conference from './page/Conference'; // ✅ Corrected import\r\n+import SmartClass from './page/SmartClass';\r\n+\r\n+import News1 from './News/News1';\r\n+import News2 from './News/News2';\r\n+import News3 from './News/News3';\r\n+import News4 from './News/News4';\r\n+import News5 from './News/News5';\r\n+import News6 from './News/News6';\r\n+import News7 from './News/News7';\r\n+\r\n+function App() {\r\n+  return (\r\n+    <>\r\n+      <BrowserRouter>\r\n+        <Routes>\r\n+          <Route path=\"/\" element={<MainContent />} />\r\n+          <Route path=\"/MA\" element={<Page1 />} />\r\n+          <Route path=\"/PhD\" element={<Page2 />} />\r\n+          <Route path=\"/About\" element={<About />} />\r\n+          <Route path=\"/Staff\" element={<Page4 />} />\r\n+          <Route path=\"/Faculty\" element={<Page5 />} />\r\n+          <Route path=\"/page6\" element={<Page6 />} />\r\n+          <Route path=\"/RoleOfSJMC\" element={<Page7 />} />\r\n+          <Route path=\"/Media_Center\" element={<Page8 />} />\r\n+          <Route path=\"/Founder_Director\" element={<Page9 />} />\r\n+          <Route path=\"/Careers\" element={<Page10 />} />\r\n+          <Route path=\"/Vision_and_mission\" element={<Page11 />} />\r\n+          <Route path=\"/Studio\" element={<Page12 />} />\r\n+          <Route path=\"/Media_lab\" element={<Page13 />} />\r\n+          <Route path=\"/Library\" element={<Page14 />} />\r\n+          <Route path=\"/page15\" element={<Page15 />} />\r\n+          <Route path=\"/page16\" element={<Page16 />} />\r\n+          <Route path=\"/Disaster_management\" element={<Page17 />} />\r\n+          <Route path=\"/Scipt_writing\" element={<Page18 />} />\r\n+          <Route path=\"/Digital_education\" element={<Page19 />} />\r\n+          <Route path=\"/Film_screening\" element={<Page20 />} />\r\n+          <Route path=\"/Refresher_training\" element={<Page21 />} />\r\n+          <Route path=\"/Student_activities\" element={<Page22 />} />\r\n+          <Route path=\"/AdvisoryCommittee\" element={<Page23 />} />\r\n+          <Route path=\"/Some_moments\" element={<Page24 />} />\r\n+          <Route path=\"/Consultant\" element={<Page25 />} />\r\n+          <Route path=\"/Page26\" element={<Page26 />} />\r\n+          <Route path=\"/Page27\" element={<Page27 />} />\r\n+          <Route path=\"/Page28\" element={<Page28 />} />\r\n+          <Route path=\"/Page29\" element={<Page29 />} />\r\n+          <Route path=\"/Page30\" element={<Page30 />} />\r\n+          <Route path=\"/upcomingEvents\" element={<Page31 />} />\r\n+          <Route path=\"/Page32\" element={<Page32 />} />\r\n+          <Route path=\"/Page33\" element={<Page33 />} />\r\n+          <Route path=\"/Page34\" element={<Page34 />} />\r\n+          <Route path=\"/Page35\" element={<Page35 />} />\r\n+          <Route path=\"/Page36\" element={<Page36 />} />\r\n+          <Route path=\"/Page37\" element={<Page37 />} />\r\n+          <Route path=\"/Page38\" element={<Page38 />} />\r\n+          <Route path=\"/Page39\" element={<Page39 />} />\r\n+          <Route path=\"/Page40\" element={<Page40 />} />\r\n+          <Route path=\"/Page41\" element={<Page41 />} />\r\n+          <Route path=\"/Page42\" element={<Page42 />} />\r\n+          <Route path=\"/Page43\" element={<Page43 />} />\r\n+          <Route path=\"/Page44\" element={<Page44 />} />\r\n+          <Route path=\"/Page45\" element={<Page45 />} />\r\n+          <Route path=\"/Page46\" element={<Page46 />} />\r\n+          <Route path=\"/Page47\" element={<Page47 />} />\r\n+          <Route path=\"/Page48\" element={<Page48 />} />\r\n+          <Route path=\"/Page49\" element={<Page49 />} />\r\n+          <Route path=\"/Page50\" element={<Page50 />} />\r\n+          <Route path=\"/Page51\" element={<Page51 />} />\r\n+          <Route path=\"/GuestFaculty\" element={<Page52 />} />\r\n+          <Route path=\"/board-of-studies\" element={<Page53 />} />\r\n+          <Route path=\"/Seminar\" element={<Seminar />} />\r\n+          <Route path=\"/Conference\" element={<Conference />} />\r\n+          <Route path=\"/SmartClass\" element={<SmartClass />} />\r\n+          <Route path=\"/News1\" element={<News1 />} />\r\n+          <Route path=\"/News2\" element={<News2 />} />\r\n+          <Route path=\"/News3\" element={<News3 />} />\r\n+          <Route path=\"/News4\" element={<News4 />} />\r\n+          <Route path=\"/News5\" element={<News5 />} />\r\n+          <Route path=\"/News6\" element={<News6 />} />\r\n+          <Route path=\"/News7\" element={<News7 />} />\r\n+        </Routes>\r\n+      </BrowserRouter>\r\n+    </>\r\n+  );\r\n+}\r\n+\r\n+export default App;\r\n"
                },
                {
                    "date": 1752086148650,
                    "content": "Index: \n===================================================================\n--- \n+++ \n@@ -53,8 +53,11 @@\n import Page50 from './page/Page50';\r\n import Page51 from './page/Page51';\r\n import Page52 from './page/Page52';\r\n import Page53 from './page/page53';\r\n+import SmartClass from './page/SmartClass';\r\n+import ConferenceRoom from './page/ConferenceRoom'; \r\n+import SeminarRoom from './page/SeminarRoom\r\n \r\n import Seminar from './page/Seminar';\r\n import Conference from './page/Conference'; // ✅ Corrected import\r\n import SmartClass from './page/SmartClass';\r\n@@ -124,161 +127,14 @@\n           <Route path=\"/Page49\" element={<Page49 />} />\r\n           <Route path=\"/Page50\" element={<Page50 />} />\r\n           <Route path=\"/Page51\" element={<Page51 />} />\r\n           <Route path=\"/GuestFaculty\" element={<Page52 />} />\r\n-          <Route path=\"/board-of-studies\" element={<Page53 />} />\r\n-          <Route path=\"/Seminar\" element={<Seminar />} />\r\n-          <Route path=\"/Conference\" element={<Conference />} />\r\n-          <Route path=\"/SmartClass\" element={<SmartClass />} />\r\n-          <Route path=\"/News1\" element={<News1 />} />\r\n-          <Route path=\"/News2\" element={<News2 />} />\r\n-          <Route path=\"/News3\" element={<News3 />} />\r\n-          <Route path=\"/News4\" element={<News4 />} />\r\n-          <Route path=\"/News5\" element={<News5 />} />\r\n-          <Route path=\"/News6\" element={<News6 />} />\r\n-          <Route path=\"/News7\" element={<News7 />} />\r\n-        </Routes>\r\n-      </BrowserRouter>\r\n-    </>\r\n-  );\r\n-}\r\n \r\n-export default App;\r\n-import React from 'react';\r\n-import MainContent from './components/Main';\r\n-import Page1 from './page/page1';\r\n-import { BrowserRouter, Route, Routes } from 'react-router-dom';\r\n-import Page2 from './page/page2';\r\n-import About from './page/About';\r\n-import Page4 from './page/Page4';\r\n-import Page5 from './page/Page5';\r\n-import Page6 from './page/Page6';\r\n-import Page7 from './page/Page7';\r\n-import Page8 from './page/Page8';\r\n-import Page9 from './page/Page9';\r\n-import Page10 from './page/Page10';\r\n-import Page11 from './page/Page11';\r\n-import Page12 from './page/Page12';\r\n-import Page13 from './page/Page13';\r\n-import Page14 from './page/Page14';\r\n-import Page15 from './page/Page15';\r\n-import Page16 from './page/Page16';\r\n-import Page17 from './page/page17';\r\n-import Page18 from './page/Page18';\r\n-import Page19 from './page/Page19';\r\n-import Page20 from './page/Page20';\r\n-import Page21 from './page/Page21';\r\n-import Page22 from './page/Page22';\r\n-import Page23 from './page/Page23';\r\n-import Page24 from './page/Page24';\r\n-import Page25 from './page/Page25';\r\n-import Page26 from './page/Page26';\r\n-import Page27 from './page/Page27';\r\n-import Page28 from './page/Page28';\r\n-import Page29 from './page/Page29';\r\n-import Page30 from './page/Page30';\r\n-import Page31 from './page/Page31';\r\n-import Page32 from './page/Page32';\r\n-import Page33 from './page/Page33';\r\n-import Page34 from './page/Page34';\r\n-import Page35 from './page/Page35';\r\n-import Page36 from './page/Page36';\r\n-import Page37 from './page/Page37';\r\n-import Page38 from './page/Page38';\r\n-import Page39 from './page/Page39';\r\n-import Page40 from './page/Page40';\r\n-import Page41 from './page/Page41';\r\n-import Page42 from './page/Page42';\r\n-import Page43 from './page/Page43';\r\n-import Page44 from './page/Page44';\r\n-import Page45 from './page/Page45';\r\n-import Page46 from './page/Page46';\r\n-import Page47 from './page/Page47';\r\n-import Page48 from './page/Page48';\r\n-import Page49 from './page/Page49';\r\n-import Page50 from './page/Page50';\r\n-import Page51 from './page/Page51';\r\n-import Page52 from './page/Page52';\r\n-import Page53 from './page/page53';\r\n-\r\n-import Seminar from './page/Seminar';\r\n-import Conference from './page/Conference'; // ✅ Corrected import\r\n-import SmartClass from './page/SmartClass';\r\n-\r\n-import News1 from './News/News1';\r\n-import News2 from './News/News2';\r\n-import News3 from './News/News3';\r\n-import News4 from './News/News4';\r\n-import News5 from './News/News5';\r\n-import News6 from './News/News6';\r\n-import News7 from './News/News7';\r\n-\r\n-function App() {\r\n-  return (\r\n-    <>\r\n-      <BrowserRouter>\r\n-        <Routes>\r\n-          <Route path=\"/\" element={<MainContent />} />\r\n-          <Route path=\"/MA\" element={<Page1 />} />\r\n-          <Route path=\"/PhD\" element={<Page2 />} />\r\n-          <Route path=\"/About\" element={<About />} />\r\n-          <Route path=\"/Staff\" element={<Page4 />} />\r\n-          <Route path=\"/Faculty\" element={<Page5 />} />\r\n-          <Route path=\"/page6\" element={<Page6 />} />\r\n-          <Route path=\"/RoleOfSJMC\" element={<Page7 />} />\r\n-          <Route path=\"/Media_Center\" element={<Page8 />} />\r\n-          <Route path=\"/Founder_Director\" element={<Page9 />} />\r\n-          <Route path=\"/Careers\" element={<Page10 />} />\r\n-          <Route path=\"/Vision_and_mission\" element={<Page11 />} />\r\n-          <Route path=\"/Studio\" element={<Page12 />} />\r\n-          <Route path=\"/Media_lab\" element={<Page13 />} />\r\n-          <Route path=\"/Library\" element={<Page14 />} />\r\n-          <Route path=\"/page15\" element={<Page15 />} />\r\n-          <Route path=\"/page16\" element={<Page16 />} />\r\n-          <Route path=\"/Disaster_management\" element={<Page17 />} />\r\n-          <Route path=\"/Scipt_writing\" element={<Page18 />} />\r\n-          <Route path=\"/Digital_education\" element={<Page19 />} />\r\n-          <Route path=\"/Film_screening\" element={<Page20 />} />\r\n-          <Route path=\"/Refresher_training\" element={<Page21 />} />\r\n-          <Route path=\"/Student_activities\" element={<Page22 />} />\r\n-          <Route path=\"/AdvisoryCommittee\" element={<Page23 />} />\r\n-          <Route path=\"/Some_moments\" element={<Page24 />} />\r\n-          <Route path=\"/Consultant\" element={<Page25 />} />\r\n-          <Route path=\"/Page26\" element={<Page26 />} />\r\n-          <Route path=\"/Page27\" element={<Page27 />} />\r\n-          <Route path=\"/Page28\" element={<Page28 />} />\r\n-          <Route path=\"/Page29\" element={<Page29 />} />\r\n-          <Route path=\"/Page30\" element={<Page30 />} />\r\n-          <Route path=\"/upcomingEvents\" element={<Page31 />} />\r\n-          <Route path=\"/Page32\" element={<Page32 />} />\r\n-          <Route path=\"/Page33\" element={<Page33 />} />\r\n-          <Route path=\"/Page34\" element={<Page34 />} />\r\n-          <Route path=\"/Page35\" element={<Page35 />} />\r\n-          <Route path=\"/Page36\" element={<Page36 />} />\r\n-          <Route path=\"/Page37\" element={<Page37 />} />\r\n-          <Route path=\"/Page38\" element={<Page38 />} />\r\n-          <Route path=\"/Page39\" element={<Page39 />} />\r\n-          <Route path=\"/Page40\" element={<Page40 />} />\r\n-          <Route path=\"/Page41\" element={<Page41 />} />\r\n-          <Route path=\"/Page42\" element={<Page42 />} />\r\n-          <Route path=\"/Page43\" element={<Page43 />} />\r\n-          <Route path=\"/Page44\" element={<Page44 />} />\r\n-          <Route path=\"/Page45\" element={<Page45 />} />\r\n-          <Route path=\"/Page46\" element={<Page46 />} />\r\n-          <Route path=\"/Page47\" element={<Page47 />} />\r\n-          <Route path=\"/Page48\" element={<Page48 />} />\r\n-          <Route path=\"/Page49\" element={<Page49 />} />\r\n-          <Route path=\"/Page50\" element={<Page50 />} />\r\n-          <Route path=\"/Page51\" element={<Page51 />} />\r\n-          <Route path=\"/GuestFaculty\" element={<Page52 />} />\r\n           <Route path=\"/board-of-studies\" element={<Page53 />} />\r\n-\r\n-          {/* ✅ Corrected routes */}\r\n           <Route path=\"/Seminar\" element={<Seminar />} />\r\n           <Route path=\"/Conference\" element={<Conference />} />\r\n           <Route path=\"/SmartClass\" element={<SmartClass />} />\r\n-\r\n-          {/* News pages */}\r\n+ \r\n           <Route path=\"/News1\" element={<News1 />} />\r\n           <Route path=\"/News2\" element={<News2 />} />\r\n           <Route path=\"/News3\" element={<News3 />} />\r\n           <Route path=\"/News4\" element={<News4 />} />\r\n"
                },
                {
                    "date": 1752086462254,
                    "content": "Index: \n===================================================================\n--- \n+++ \n@@ -53,11 +53,8 @@\n import Page50 from './page/Page50';\r\n import Page51 from './page/Page51';\r\n import Page52 from './page/Page52';\r\n import Page53 from './page/page53';\r\n-import SmartClass from './page/SmartClass';\r\n-import ConferenceRoom from './page/ConferenceRoom'; \r\n-import SeminarRoom from './page/SeminarRoom\r\n \r\n import Seminar from './page/Seminar';\r\n import Conference from './page/Conference'; // ✅ Corrected import\r\n import SmartClass from './page/SmartClass';\r\n"
                },
                {
                    "date": 1753841601950,
                    "content": "Index: \n===================================================================\n--- \n+++ \n@@ -41,8 +41,9 @@\n import Page35 from './page/Page35';\r\n import Page36 from './page/Page36';\r\n import Page37 from './page/Page37';\r\n import Page54 from './page/Page54';\r\n+import PKAHANI from './page/PKAHANI';\r\n import Page38 from './page/Page38';\r\n import Page39 from './page/Page39';\r\n import Page40 from './page/Page40';\r\n import Page41 from './page/Page41';\r\n@@ -143,8 +144,9 @@\n           <Route path=\"/Page47\" element={<Page47 />} />\r\n           <Route path=\"/Page48\" element={<Page48 />} />\r\n           <Route path=\"/Page49\" element={<Page49 />} />\r\n           <Route path=\"/Page50\" element={<Page50 />} />\r\n+          <Route path=\"/PKAHANI\" element={<PKAHANI />} />\r\n           <Route path=\"/Page51\" element={<Page51 />} />\r\n           <Route path=\"/GuestFaculty\" element={<Page52 />} />\r\n           <Route path=\"/board-of-studies\" element={<Page53 />} />\r\n           <Route path=\"/Seminar\" element={<Seminar />} />\r\n"
                }
            ],
            "date": 1752058703396,
            "name": "Commit-0",
            "content": "import React from 'react';\r\nimport MainContent from './components/Main';\r\nimport Page1 from './page/page1';\r\nimport { BrowserRouter, Route, Routes } from 'react-router-dom';\r\nimport Page2 from './page/page2';\r\nimport About from './page/About';\r\nimport Page4 from './page/Page4';\r\nimport Page5 from './page/Page5';\r\nimport Page6 from './page/Page6';\r\nimport Page7 from './page/Page7';\r\nimport Page8 from './page/Page8';\r\nimport Page9 from './page/Page9';\r\nimport Page10 from './page/Page10';\r\nimport Page11 from './page/Page11';\r\nimport Page12 from './page/Page12';\r\nimport Page13 from './page/Page13';\r\nimport Page14 from './page/Page14';\r\nimport Page15 from './page/Page15';\r\nimport Page16 from './page/Page16';\r\nimport Page17 from './page/page17';\r\nimport Page18 from './page/Page18';\r\nimport Page19 from './page/Page19';\r\nimport Page20 from './page/Page20';\r\nimport Page21 from './page/Page21';\r\nimport Page22 from './page/Page22';\r\nimport Page23 from './page/Page23';\r\nimport Page24 from './page/Page24';\r\nimport Page25 from './page/Page25';\r\nimport Page26 from './page/Page26';\r\nimport Page27 from './page/Page27';\r\nimport Page28 from './page/Page28';\r\nimport Page29 from './page/Page29';\r\nimport Page30 from './page/Page30';\r\nimport Page31 from './page/Page31';\r\nimport Page32 from './page/Page32';\r\nimport Page33 from './page/Page33';\r\nimport Page34 from './page/Page34';\r\nimport Page35 from './page/Page35';\r\nimport Page36 from './page/Page36';\r\nimport Page37 from './page/Page37';\r\nimport Page38 from './page/Page38';\r\nimport Page39 from './page/Page39';\r\nimport Page40 from './page/Page40';\r\nimport Page41 from './page/Page41';\r\nimport Page42 from './page/Page42';\r\nimport Page43 from './page/Page43';\r\nimport Page44 from './page/Page44';\r\nimport Page45 from './page/Page45';\r\nimport Page46 from './page/Page46';\r\nimport Page47 from './page/Page47';\r\nimport Page48 from './page/Page48';\r\nimport Page49 from './page/Page49';\r\nimport Page50 from './page/Page50';\r\nimport Page51 from './page/Page51';\r\nimport Page52 from './page/Page52';\r\nimport Page53 from './page/page53';\r\nimport Seminar from './page/Seminar';\r\nimport Conference from './page/Conference';\r\nimport SmartClass from './page/SmartClass';\r\n\r\n\r\n\r\nimport News1 from './News/News1';\r\nimport News2 from './News/News2';\r\nimport News3 from './News/News3';\r\nimport News4 from './News/News4';\r\nimport News5 from './News/News5';\r\nimport News6 from './News/News6';\r\nimport News7 from './News/News7';\r\n\r\n\r\n\r\n\r\nfunction App() {\r\n  return (\r\n    < >\r\n      \r\n      <BrowserRouter>\r\n      \r\n        <Routes>\r\n        <Route path=\"/\" element={<MainContent />} />\r\n          <Route path=\"/MA\" element={<Page1 />} />\r\n          <Route path=\"/PhD\" element={<Page2 />} />\r\n          <Route path=\"/About\" element={<About />} />\r\n          <Route path=\"/Staff\" element={<Page4 />} />\r\n          <Route path=\"/Faculty\" element={<Page5 />} />\r\n          <Route path=\"/page6\" element={<Page6 />} />\r\n          <Route path=\"/RoleOfSJMC\" element={<Page7 />} />\r\n          <Route path=\"/Media_Center\" element={<Page8 />} />\r\n          <Route path=\"/Founder_Director\" element={<Page9 />} />\r\n          <Route path=\"/Careers\" element={<Page10 />} />\r\n          <Route path=\"/Vision_and_mission\" element={<Page11 />} />\r\n          <Route path=\"/Studio\" element={<Page12 />} />\r\n          <Route path=\"/Media_lab\" element={<Page13 />} />\r\n          <Route path=\"/Library\" element={<Page14 />} />\r\n          <Route path=\"/page15\" element={<Page15 />} />\r\n          <Route path=\"/page16\" element={<Page16 />} />\r\n          <Route path=\"/Disaster_management\" element={<Page17 />} />\r\n          <Route path=\"/Digital_education\" element={<Page19 />} />\r\n          <Route path=\"/Film_screening\" element={<Page20 />} />\r\n          <Route path=\"/Scipt_writing\" element={<Page18 />} />\r\n          <Route path=\"/Refresher_training\" element={<Page21 />} />\r\n          <Route path=\"/Student_activities\" element={<Page22 />} />\r\n          <Route path=\"/AdvisoryCommittee\" element={<Page23 />} />\r\n          <Route path=\"/Some_moments\" element={<Page24 />} />\r\n          <Route path=\"/Consultant\" element={<Page25 />} />\r\n          <Route path=\"/Page26\" element={<Page26 />} />\r\n          <Route path=\"/Page27\" element={<Page27 />} />\r\n          <Route path=\"/Page28\" element={<Page28 />} />\r\n          <Route path=\"/Page29\" element={<Page29 />} />\r\n          <Route path=\"/Page30\" element={<Page30 />} />\r\n          <Route path=\"/upcomingEvents\" element={<Page31 />} />\r\n          <Route path=\"/Page32\" element={<Page32 />} />\r\n          <Route path=\"/Page33\" element={<Page33 />} />\r\n          <Route path=\"/Page34\" element={<Page34 />} />\r\n          <Route path=\"/Page35\" element={<Page35 />} />\r\n          <Route path=\"/Page36\" element={<Page36 />} />\r\n          <Route path=\"/Page37\" element={<Page37 />} />\r\n          <Route path=\"/Page38\" element={<Page38 />} />\r\n          <Route path=\"/Page39\" element={<Page39/>} />\r\n          <Route path=\"/Page40\" element={<Page40/>} />\r\n          <Route path=\"/Page41\" element={<Page41/>} />\r\n          <Route path=\"/Page42\" element={<Page42/>} />\r\n          <Route path=\"/Page44\" element={<Page44/>} />\r\n          <Route path=\"/Page43\" element={<Page43/>} />\r\n          <Route path=\"/Page45\" element={<Page45/>} />\r\n          <Route path=\"/Page46\" element={<Page46/>} />\r\n          <Route path=\"/Page47\" element={<Page47/>} />\r\n          <Route path=\"/Page48\" element={<Page48/>} />\r\n          <Route path=\"/Page49\" element={<Page49/>} />\r\n          <Route path=\"/Page50\" element={<Page50/>} />\r\n          <Route path=\"/Page51\" element={<Page51/>} />\r\n          <Route path=\"/GuestFaculty\" element={<Page52 />} />\r\n         <Route path=\"/board-of-studies\" element={<Page53 />} />\r\n         <Route path=\"/Seminar\" element={<Seminar />} />\r\n        <Route path=\"/Conference\" element={<Conference />} />\r\n        <Route path=\"/SmartClass\" element={<SmartClass />} />\r\n        </Routes>\r\n\r\n\r\n\r\n\r\n          \r\n          \r\n          <Route path=\"/News1\" element={<News1 />} />\r\n          <Route path=\"/News2\" element={<News2 />} />\r\n          <Route path=\"/News3\" element={<News3 />} />\r\n          <Route path=\"/News4\" element={<News4 />} />\r\n          <Route path=\"/News5\" element={<News5 />} />\r\n          <Route path=\"/News6\" element={<News6 />} />\r\n          <Route path=\"/News7\" element={<News7 />} />\r\n        </Routes>\r\n       \r\n      </BrowserRouter>\r\n      \r\n    </ >\r\n  );\r\n}\r\n\r\nexport default App;\r\n"
        }
    ]
}